_version.py
alegra/__init__.py
alegra/_version.py
alegra/client.py
alegra/config.py
alegra/models/__init__.py
alegra/models/address.py
alegra/models/company.py
alegra/models/customer.py
alegra/models/dian.py
alegra/models/invoice.py
alegra/models/note.py
alegra/models/payroll.py
alegra/models/phone_number.py
alegra/models/test_set.py
alegra/resources/__init__.py
alegra/resources/base.py
alegra/resources/factory.py
alegra_e_provider-0.0.6.dist-info/METADATA
alegra_e_provider-0.0.6.dist-info/WHEEL
alegra_e_provider-0.0.6.dist-info/top_level.txt
alegra_e_provider-0.0.6.dist-info/RECORD
